sysspeaker/__init__.py
sysspeaker/sysspeaker.py
sysspeaker-0.1.2.dist-info/LICENSE
sysspeaker-0.1.2.dist-info/METADATA
sysspeaker-0.1.2.dist-info/WHEEL
sysspeaker-0.1.2.dist-info/top_level.txt
sysspeaker-0.1.2.dist-info/RECORD
